odoo/addons/mail_send_confirmation/README.rst
odoo/addons/mail_send_confirmation/__init__.py
odoo/addons/mail_send_confirmation/__manifest__.py
odoo/addons/mail_send_confirmation/i18n/es.po
odoo/addons/mail_send_confirmation/i18n/it.po
odoo/addons/mail_send_confirmation/i18n/ja.po
odoo/addons/mail_send_confirmation/i18n/mail_send_confirmation.pot
odoo/addons/mail_send_confirmation/readme/CONTRIBUTORS.md
odoo/addons/mail_send_confirmation/readme/DESCRIPTION.md
odoo/addons/mail_send_confirmation/static/description/icon.png
odoo/addons/mail_send_confirmation/static/description/index.html
odoo/addons/mail_send_confirmation/static/src/models/composer_view.esm.js
odoo_addon_mail_send_confirmation-18.0.1.0.0.5.dist-info/METADATA
odoo_addon_mail_send_confirmation-18.0.1.0.0.5.dist-info/WHEEL
odoo_addon_mail_send_confirmation-18.0.1.0.0.5.dist-info/top_level.txt
odoo_addon_mail_send_confirmation-18.0.1.0.0.5.dist-info/RECORD
